{
  "HALProvider": {
    "Other Devices": {
      "Talon FX[11]": {
        "header": {
          "open": true
        }
      },
      "Talon SRX[20]": {
        "header": {
          "open": true
        }
      },
      "Talon SRX[4]": {
        "header": {
          "open": true
        }
      },
      "Talon SRX[4]/Quad Encoder": {
        "header": {
          "open": true
        }
      }
    },
    "Timing": {
      "window": {
        "visible": false
      }
    }
  },
  "NTProvider": {
    "types": {
      "/FMSInfo": "FMSInfo",
      "/SmartDashboard/Auto Chooser": "String Chooser",
      "/SmartDashboard/Drive": "Subsystem",
      "/SmartDashboard/Field": "Field2d",
      "/SmartDashboard/Scheduler": "Scheduler",
      "/SmartDashboard/String Chooser": "String Chooser",
      "/SmartDashboard/Vision": "Subsystem"
    },
    "windows": {
      "/SmartDashboard/Auto Chooser": {
        "window": {
          "visible": true
        }
      },
      "/SmartDashboard/Field": {
        "image": "C:\\Users\\Team4572Admin\\Documents\\FRC2023\\field23 - Blue Alliance.png",
        "window": {
          "visible": true
        }
      }
    }
  },
  "NetworkTables": {
    "transitory": {
      "SmartDashboard": {
        "Drive": {
          "open": true
        },
        "Field": {
          "open": true
        },
        "Index": {
          "open": true
        },
        "Shooter": {
          "open": true
        }
      },
      "drive": {
        "odometry": {
          "open": true
        },
        "open": true,
        "pose": {
          "open": true
        }
      },
      "pathPlanner": {
        "open": true,
        "rotationError": {
          "open": true
        },
        "setpointSpeeds": {
          "open": true
        },
        "targetPose": {
          "open": true
        },
        "translationError": {
          "open": true
        }
      },
      "shooter": {
        "open": true
      }
    }
  },
  "Plot": {
    "Plot <0>": {
      "plots": [
        {
          "height": 474,
          "series": [
            {
              "color": [
                0.3333333432674408,
                0.658823549747467,
                0.4078431725502014,
                1.0
              ],
              "id": "NT:pathPlanner/targetPose/X"
            },
            {
              "color": [
                0.7686275243759155,
                0.30588236451148987,
                0.32156863808631897,
                1.0
              ],
              "id": "NT:pathPlanner/targetPose/Y"
            },
            {
              "color": [
                0.3333333432674408,
                0.36629441380500793,
                0.658823549747467,
                1.0
              ],
              "id": "NT:drive/odometry/X"
            },
            {
              "color": [
                0.7510549426078796,
                0.7686275243759155,
                0.30588236451148987,
                1.0
              ],
              "id": "NT:drive/odometry/Y"
            }
          ]
        }
      ]
    }
  }
}
